binance_sdk_fiat/__init__.py
binance_sdk_fiat/fiat.py
binance_sdk_fiat/metadata.py
binance_sdk_fiat/rest_api/__init__.py
binance_sdk_fiat/rest_api/api/__init__.py
binance_sdk_fiat/rest_api/api/fiat_api.py
binance_sdk_fiat/rest_api/models/__init__.py
binance_sdk_fiat/rest_api/models/account_info.py
binance_sdk_fiat/rest_api/models/deposit_response.py
binance_sdk_fiat/rest_api/models/deposit_response_data.py
binance_sdk_fiat/rest_api/models/enums.py
binance_sdk_fiat/rest_api/models/fiat_withdraw_response.py
binance_sdk_fiat/rest_api/models/get_fiat_deposit_withdraw_history_response.py
binance_sdk_fiat/rest_api/models/get_fiat_deposit_withdraw_history_response_data_inner.py
binance_sdk_fiat/rest_api/models/get_fiat_payments_history_response.py
binance_sdk_fiat/rest_api/models/get_fiat_payments_history_response_data_inner.py
binance_sdk_fiat/rest_api/models/get_order_detail_response.py
binance_sdk_fiat/rest_api/models/get_order_detail_response_data.py
binance_sdk_fiat/rest_api/rest_api.py
binance_sdk_fiat-5.1.0.dist-info/METADATA
binance_sdk_fiat-5.1.0.dist-info/WHEEL
binance_sdk_fiat-5.1.0.dist-info/licenses/LICENCE
binance_sdk_fiat-5.1.0.dist-info/RECORD
